{"resource":"V1::FormTemplatesController","action":"index","status":200,"description":"200 and all FormTemplates for the current user","error":false,"lecturer":true,"request_params":"{}","response_body":"{\"form_templates\":[{\"id\":1,\"name\":\"Hennepin Template\",\"lecturer_id\":1,\"questions\":[{\"text\":\"Do you collect anything?\",\"type_id\":1,\"question_id\":1,\"question_type\":{\"id\":1,\"question_type\":\"text\",\"friendly_name\":\"name\"}},{\"text\":\"Have you ever been professionally photographed?\",\"type_id\":1,\"question_id\":2,\"question_type\":{\"id\":1,\"question_type\":\"text\",\"friendly_name\":\"name\"}},{\"text\":\"Do you prefer Honey or Jam?\",\"type_id\":1,\"question_id\":3,\"question_type\":{\"id\":1,\"question_type\":\"text\",\"friendly_name\":\"name\"}},{\"text\":\"What do you think the greatest invention has been?\",\"type_id\":1,\"question_id\":4,\"question_type\":{\"id\":1,\"question_type\":\"text\",\"friendly_name\":\"name\"}},{\"text\":\"If you were to join an emergency service which would it be?\",\"type_id\":1,\"question_id\":5,\"question_type\":{\"id\":1,\"question_type\":\"text\",\"friendly_name\":\"name\"}}]},{\"id\":2,\"name\":\"Péché Mortel Template\",\"lecturer_id\":1,\"questions\":[{\"text\":\"Have you ever been approached by someone who knew you but you couldn't remember them for the life of you?\",\"type_id\":1,\"question_id\":1,\"question_type\":{\"id\":1,\"question_type\":\"text\",\"friendly_name\":\"name\"}},{\"text\":\"What are cooler? Dinosaurs or Dragons?\",\"type_id\":1,\"question_id\":2,\"question_type\":{\"id\":1,\"question_type\":\"text\",\"friendly_name\":\"name\"}},{\"text\":\"What do you think the greatest invention has been?\",\"type_id\":1,\"question_id\":3,\"question_type\":{\"id\":1,\"question_type\":\"text\",\"friendly_name\":\"name\"}},{\"text\":\"Have you ever tossed your own pancake?\",\"type_id\":1,\"question_id\":4,\"question_type\":{\"id\":1,\"question_type\":\"text\",\"friendly_name\":\"name\"}},{\"text\":\"At what age did you twig onto the fact Santa wasnt real?\",\"type_id\":1,\"question_id\":5,\"question_type\":{\"id\":1,\"question_type\":\"text\",\"friendly_name\":\"name\"}}]}]}","response_headers":{"X-Frame-Options":"SAMEORIGIN","X-XSS-Protection":"1; mode=block","X-Content-Type-Options":"nosniff","Content-Type":"application/json; charset=utf-8"}}
