{"resource":"V1::UnitsController","action":"archive","status":200,"description":"responds with 200 if unit was archived successfully","error":false,"lecturer":true,"request_params":"{\"id\":\"29\"}","response_body":"{\"unit\":{\"id\":29,\"name\":\"Unit 447\",\"code\":\"uesyg+DxeX5lHw==\",\"semester\":\"Spring\",\"year\":2015,\"archived_at\":\"2017-03-09\",\"department\":{\"id\":32,\"university\":\"University of 77083\",\"name\":\"Computer Science73215\"}}}","response_headers":{"X-Frame-Options":"SAMEORIGIN","X-XSS-Protection":"1; mode=block","X-Content-Type-Options":"nosniff","Content-Type":"application/json; charset=utf-8"}}
